LICENSE
README.md
pyproject.toml
setup.py
smartnoise_synth_logger/__init__.py
smartnoise_synth_logger/constants.py
smartnoise_synth_logger/deserialise.py
smartnoise_synth_logger/serialise.py
smartnoise_synth_logger.egg-info/PKG-INFO
smartnoise_synth_logger.egg-info/SOURCES.txt
smartnoise_synth_logger.egg-info/dependency_links.txt
smartnoise_synth_logger.egg-info/requires.txt
smartnoise_synth_logger.egg-info/top_level.txt
tests/test_de_serialisation.py