Metadata-Version: 2.1
Name: smartnoise_synth_logger
Version: 0.0.4
Summary: A logger wrapper for Smartnoise Synth Table Transformer
Home-page: https://github.com/dscc-admin/lomas/
Author: Data Science Competence Center, Swiss Federal Statistical Office
Author-email: dscc@bfs.admin.ch
License: MIT
Keywords: smartnoise-synth,logger,serialiser,deserialiser
Classifier: Development Status :: 3 - Alpha
Classifier: Intended Audience :: Developers
Classifier: License :: OSI Approved :: MIT License
Classifier: Programming Language :: Python :: 3.11
Requires-Python: >=3.10, <4
License-File: LICENSE
Requires-Dist: smartnoise-synth==1.0.4
